setup.py
hfcronnix/__init__.py
hfcronnix.egg-info/PKG-INFO
hfcronnix.egg-info/SOURCES.txt
hfcronnix.egg-info/dependency_links.txt
hfcronnix.egg-info/requires.txt
hfcronnix.egg-info/top_level.txt