Metadata-Version: 2.1
Name: hfcronnix
Version: 0.2
Summary: Cronnix Setter using puautogui
Author: VishalJain_NIOT
Author-email: vishaljain9516@gmail.com
